polarparrot/__init__.py
polarparrot/analytics_list.json
polarparrot/app.py
polarparrot/backend_service.py
polarparrot/calculation_engine.py
polarparrot/data_service.py
polarparrot/metrics_runner.py
polarparrot/start_services.sh
polarparrot/data/data.py
polarparrot/data/data.sql
polarparrot/data/generate_positions_json.py
polarparrot/data/positions_20k_precise.json
polarparrot/docs/Makefile
polarparrot/docs/conf.py
polarparrot/docs/make.bat
polarparrot/docs/solution_diagram.py
polarparrot/docs/source/calculation_engine.rst
polarparrot/docs/source/conf.py
polarparrot/docs/source/data.rst
polarparrot/docs/source/index.rst
polarparrot/docs/source/metrics_runner.rst
polarparrot/docs/source/modules.rst
polarparrot/gpt/gpt_service.py
polarparrot/gpt/sample_yaml_prompts.txt
polarparrot/pdfcompare/pdfcompare.py
polarparrot/tests/regression_runner.py
polarparrot/tests/unit_tests_runner.py
polarparrot/yaml/0001.yaml
polarparrot/yaml/0002.yaml
polarparrot/yaml/0003.yaml
polarparrot/yaml/0004.yaml
polarparrot/yaml/0005.yaml
polarparrot/yaml/validate_yaml.py
polarparrot/yaml/yaml_schema.json
polarparrot-0.0.12.dist-info/METADATA
polarparrot-0.0.12.dist-info/WHEEL
polarparrot-0.0.12.dist-info/top_level.txt
polarparrot-0.0.12.dist-info/RECORD
