Metadata-Version: 2.1
Name: polarparrot
Version: 0.0.12
Summary: Modular YAML based portfolio analytics calculation engine
Home-page: https://github.com/maxicusj/polarparrot
Author: Roman Maxymchuk
Author-email: rom555@me.com
Project-URL: Bug Tracker, https://github.com/maxicusj/polarparrot/issues
Classifier: Programming Language :: Python :: 3
Classifier: License :: OSI Approved :: MIT License
Classifier: Operating System :: OS Independent
Requires-Python: >=3.11
Requires-Dist: pyodbc>=5.2.0
Requires-Dist: PyYAML>=6.0.2
Requires-Dist: pyarrow>=18.0.0
Requires-Dist: polars>=1.14.0
Provides-Extra: dev
Requires-Dist: pytest; extra == "dev"
Requires-Dist: black; extra == "dev"
Requires-Dist: isort; extra == "dev"
